Workbook
Name GrowthRate: Assumptions!$B$2
Name COGSMargin: Assumptions!$B$3
Name TaxRate: Assumptions!$B$5
Name WACC: Assumptions!$B$6
Name InitialRevenue: Assumptions!$B$7

Sheet Assumptions
A1: Parameter | B1: Value | C1: Unit | D1: Notes
A2: Revenue Growth Rate | B2: 0.08 | C2: % | D2: Year-over-year
A3: COGS Margin | B3: 0.45 | C3: % | D3: % of revenue
A4: OpEx Growth Rate | B4: 0.05 | C4: % | D4: Annual increase
A5: Tax Rate | B5: 0.21 | C5: % | D5: Federal + State
A6: Discount Rate (WACC) | B6: 0.1 | C6: % | D6: Risk-adjusted
A7: Initial Revenue | B7: 10000000 | C7: $ | D7: Year 0 baseline
A8: Initial OpEx | B8: 3000000 | C8: $ | D8: Year 0 baseline
A9: CapEx (Annual) | B9: 500000 | C9: $ | D9: Flat assumption
A10: Working Capital % Rev | B10: 0.12 | C10: % | D10: NWC/Revenue
A11: Terminal Growth Rate | B11: 0.025 | C11: % | D11: Long-term GDP

Sheet P&L
A1: Income Statement
B2: Year 1 | C2: Year 2 | D2: Year 3 | E2: Year 4 | F2: Year 5
A3: Revenue | B3: =Assumptions!B7*(1+Assumptions!B2) | C3: =B3*(1+Assumptions!$B$2) | D3: =C3*(1+Assumptions!$B$2) | E3: =D3*(1+Assumptions!$B$2) | F3: =E3*(1+Assumptions!$B$2)
A4: COGS | B4: =-B3*Assumptions!$B$3 | C4: =-C3*Assumptions!$B$3 | D4: =-D3*Assumptions!$B$3 | E4: =-E3*Assumptions!$B$3 | F4: =-F3*Assumptions!$B$3
A5: Gross Profit | B5: =B3+B4 | C5: =C3+C4 | D5: =D3+D4 | E5: =E3+E4 | F5: =F3+F4
A6: Operating Expenses | B6: =-Assumptions!B8*(1+Assumptions!B4) | C6: =B6*(1+Assumptions!$B$4) | D6: =C6*(1+Assumptions!$B$4) | E6: =D6*(1+Assumptions!$B$4) | F6: =E6*(1+Assumptions!$B$4)
A7: EBIT | B7: =B5+B6 | C7: =C5+C6 | D7: =D5+D6 | E7: =E5+E6 | F7: =F5+F6
A8: Tax | B8: =-MAX(B7*Assumptions!$B$5,0) | C8: =-MAX(C7*Assumptions!$B$5,0) | D8: =-MAX(D7*Assumptions!$B$5,0) | E8: =-MAX(E7*Assumptions!$B$5,0) | F8: =-MAX(F7*Assumptions!$B$5,0)
A9: Net Income | B9: =B7+B8 | C9: =C7+C8 | D9: =D7+D8 | E9: =E7+E8 | F9: =F7+F8

Sheet Summary
A1: 5-Year Financial Summary
A3: Total Revenue (5yr) | B3: =SUM('P&L'!B3:F3)
A4: Total Net Income (5yr) | B4: =SUM('P&L'!B9:F9)
A5: Average Net Margin | B5: =B4/B3
